{"errors":[],"warnings":[],"namedChunkGroups":{"app":{"chunks":[6,0,2],"assets":["webpack-runtime-3c64aa8c4edc56811158.js","commons-9c4baca6725c882cd918.js","app-e1a0a7569c2ddc8fc61b.js"],"children":{},"childAssets":{}},"component---src-pages-404-js":{"chunks":[1,0,3],"assets":["styles.72b5dc762eaf09d9d043.css","styles-f3bae639b1c3b6449343.js","commons-9c4baca6725c882cd918.js","component---src-pages-404-js-6f677eb56565cbf7c07e.js"],"children":{},"childAssets":{}},"component---src-pages-index-js":{"chunks":[1,0,4],"assets":["styles.72b5dc762eaf09d9d043.css","styles-f3bae639b1c3b6449343.js","commons-9c4baca6725c882cd918.js","component---src-pages-index-js-df69e80d9b74eb076d09.js"],"children":{},"childAssets":{}},"component---src-pages-privacy-js":{"chunks":[1,0,5],"assets":["styles.72b5dc762eaf09d9d043.css","styles-f3bae639b1c3b6449343.js","commons-9c4baca6725c882cd918.js","component---src-pages-privacy-js-bff57ab44b6d53164b15.js"],"children":{},"childAssets":{}}},"assetsByChunkName":{"app":["webpack-runtime-3c64aa8c4edc56811158.js","commons-9c4baca6725c882cd918.js","app-e1a0a7569c2ddc8fc61b.js"],"component---src-pages-404-js":["styles.72b5dc762eaf09d9d043.css","styles-f3bae639b1c3b6449343.js","commons-9c4baca6725c882cd918.js","component---src-pages-404-js-6f677eb56565cbf7c07e.js"],"component---src-pages-index-js":["styles.72b5dc762eaf09d9d043.css","styles-f3bae639b1c3b6449343.js","commons-9c4baca6725c882cd918.js","component---src-pages-index-js-df69e80d9b74eb076d09.js"],"component---src-pages-privacy-js":["styles.72b5dc762eaf09d9d043.css","styles-f3bae639b1c3b6449343.js","commons-9c4baca6725c882cd918.js","component---src-pages-privacy-js-bff57ab44b6d53164b15.js"]}}